avideo-2017.9.27.dist-info/WHEEL
avideo-2017.9.27.dist-info/top_level.txt
avideo-2017.9.27.dist-info/metadata.json
avideo-2017.9.27.dist-info/RECORD
avideo-2017.9.27.dist-info/METADATA
avideo-2017.9.27.dist-info/DESCRIPTION.rst
avideo-2017.9.27.dist-info/entry_points.txt
avideo-2017.9.27.data/data/share/doc/avideo/README.txt
avideo-2017.9.27.data/data/share/man/man1/avideo.1
avideo-2017.9.27.data/data/etc/bash_completion.d/avideo.bash-completion
avideo-2017.9.27.data/data/etc/fish/completions/avideo.fish
avideo/compat.py
avideo/YoutubeDL.py
avideo/socks.py
avideo/version.py
avideo/__main__.py
avideo/__init__.py
avideo/aes.py
avideo/cache.py
avideo/options.py
avideo/utils.py
avideo/downloader/f4m.py
avideo/downloader/external.py
avideo/downloader/http.py
avideo/downloader/hls.py
avideo/downloader/rtsp.py
avideo/downloader/fragment.py
avideo/downloader/rtmp.py
avideo/downloader/dash.py
avideo/downloader/ism.py
avideo/downloader/__init__.py
avideo/downloader/common.py
avideo/extractor/nytimes.py
avideo/extractor/radiode.py
avideo/extractor/cinchcast.py
avideo/extractor/twentyfourvideo.py
avideo/extractor/gameone.py
avideo/extractor/audioboom.py
avideo/extractor/rtlnl.py
avideo/extractor/esri.py
avideo/extractor/sina.py
avideo/extractor/reddit.py
avideo/extractor/imdb.py
avideo/extractor/porn91.py
avideo/extractor/azmedien.py
avideo/extractor/patreon.py
avideo/extractor/vh1.py
avideo/extractor/ard.py
avideo/extractor/nhk.py
avideo/extractor/xnxx.py
avideo/extractor/ign.py
avideo/extractor/jove.py
avideo/extractor/clipsyndicate.py
avideo/extractor/ebaumsworld.py
avideo/extractor/howcast.py
avideo/extractor/noco.py
avideo/extractor/vyborymos.py
avideo/extractor/hornbunny.py
avideo/extractor/tunein.py
avideo/extractor/kontrtube.py
avideo/extractor/spike.py
avideo/extractor/uol.py
avideo/extractor/miaopai.py
avideo/extractor/vice.py
avideo/extractor/channel9.py
avideo/extractor/nosvideo.py
avideo/extractor/jeuxvideo.py
avideo/extractor/dotsub.py
avideo/extractor/twitch.py
avideo/extractor/bpb.py
avideo/extractor/laola1tv.py
avideo/extractor/vgtv.py
avideo/extractor/tubitv.py
avideo/extractor/europa.py
avideo/extractor/shahid.py
avideo/extractor/usanetwork.py
